<?xml version="1.0" encoding="utf-8" ?>
<dwsync>
<file name="bootstrap_1492712499.css" server="E:/XAMPP/htdocs/moradiyabros.in/" local="131371860990000000" remote="131371860990000000" Dst="0" />
<file name="bootstrap_1492712510.css" server="E:/XAMPP/htdocs/moradiyabros.in/" local="131371861100000000" remote="131371861100000000" Dst="0" />
<file name="bootstrap_1492712512.css" server="E:/XAMPP/htdocs/moradiyabros.in/" local="131371861120000000" remote="131371861120000000" Dst="0" />
<file name="bootstrap_1492712519.css" server="E:/XAMPP/htdocs/moradiyabros.in/" local="131371861190000000" remote="131371861190000000" Dst="0" />
<file name="bootstrap_1492712574.css" server="E:/XAMPP/htdocs/moradiyabros.in/" local="131371861740000000" remote="131371861740000000" Dst="0" />
<file name="bootstrap_1492712589.css" server="E:/XAMPP/htdocs/moradiyabros.in/" local="131371861890000000" remote="131371861890000000" Dst="0" />
<file name="bootstrap_1492712600.css" server="E:/XAMPP/htdocs/moradiyabros.in/" local="131371862000000000" remote="131371862000000000" Dst="0" />
<file name="bootstrap_1492712605.css" server="E:/XAMPP/htdocs/moradiyabros.in/" local="131371862050000000" remote="131371862050000000" Dst="0" />
<file name="bootstrap_1492712608.css" server="E:/XAMPP/htdocs/moradiyabros.in/" local="131371862080000000" remote="131371862080000000" Dst="0" />
<file name="bootstrap_1492712615.css" server="E:/XAMPP/htdocs/moradiyabros.in/" local="131371862150000000" remote="131371862150000000" Dst="0" />
<file name="bootstrap_1492712618.css" server="E:/XAMPP/htdocs/moradiyabros.in/" local="131371862180000000" remote="131371862180000000" Dst="0" />
<file name="bootstrap_1492712624.css" server="E:/XAMPP/htdocs/moradiyabros.in/" local="131371862240000000" remote="131371862240000000" Dst="0" />
<file name="bootstrap_1492712631.css" server="E:/XAMPP/htdocs/moradiyabros.in/" local="131371862310000000" remote="131371862310000000" Dst="0" />
<file name="bootstrap_1492712636.css" server="E:/XAMPP/htdocs/moradiyabros.in/" local="131371862360000000" remote="131371862360000000" Dst="0" />
<file name="bootstrap_1492712653.css" server="E:/XAMPP/htdocs/moradiyabros.in/" local="131371862540000000" remote="131371862540000000" Dst="0" />
<file name="bootstrap_1492712654.css" server="E:/XAMPP/htdocs/moradiyabros.in/" local="131371862540000000" remote="131371862540000000" Dst="0" />
<file name="bootstrap_1492712659.css" server="E:/XAMPP/htdocs/moradiyabros.in/" local="131371862590000000" remote="131371862590000000" Dst="0" />
<file name="bootstrap_1492712701.css" server="E:/XAMPP/htdocs/moradiyabros.in/" local="131371863010000000" remote="131371863010000000" Dst="0" />
<file name="bootstrap_1492712709.css" server="E:/XAMPP/htdocs/moradiyabros.in/" local="131371863090000000" remote="131371863090000000" Dst="0" />
<file name="bootstrap_1492712740.css" server="E:/XAMPP/htdocs/moradiyabros.in/" local="131371863400000000" remote="131371863400000000" Dst="0" />
</dwsync>